biogemeutilities/__init__.py
biogemeutilities/biogeme.py
biogemeutilities/database.py
biogemeutilities/filenames.py
biogemeutilities/statistics.py
biogemeutilities-1.0.5.dist-info/LICENSE.txt
biogemeutilities-1.0.5.dist-info/METADATA
biogemeutilities-1.0.5.dist-info/WHEEL
biogemeutilities-1.0.5.dist-info/top_level.txt
biogemeutilities-1.0.5.dist-info/RECORD
