Metadata-Version: 2.1
Name: biogemeutilities
Version: 1.0.5
Summary: Add features to the biogeme package
Home-page: 
Author: Mikkel Thorhauge
Author-email: 
License: MIT
Keywords: biogeme,discrete choice models,confidence interval,calibrate
Classifier: Development Status :: 5 - Production/Stable
Classifier: Intended Audience :: Science/Research
Classifier: License :: OSI Approved :: MIT License
Classifier: Operating System :: OS Independent
Classifier: Programming Language :: Python :: 3
Classifier: Topic :: Scientific/Engineering
Requires-Python: >=3.8.18
License-File: LICENSE.txt
Requires-Dist: biogeme >=3.2.12
Requires-Dist: pandas >=2.0.3
Requires-Dist: numpy >=1.24.3
Requires-Dist: xlsxwriter >=3.1.2
